MANIFEST.in
Makefile
README.rst
RELEASE.md
setup.cfg
setup.py
idl/thrift/zipkincore.thrift
jaeger_client_contrib/__init__.py
jaeger_client_contrib/config.py
jaeger_client_contrib/sampler.py
jaeger_client_contrib/thrift.py
jaeger_client_contrib/tracer.py
jaeger_client_contrib.egg-info/PKG-INFO
jaeger_client_contrib.egg-info/SOURCES.txt
jaeger_client_contrib.egg-info/dependency_links.txt
jaeger_client_contrib.egg-info/not-zip-safe
jaeger_client_contrib.egg-info/requires.txt
jaeger_client_contrib.egg-info/top_level.txt
jaeger_client_contrib/thrift_gen/__init__.py
jaeger_client_contrib/thrift_gen/zipkincore/__init__.py
jaeger_client_contrib/thrift_gen/zipkincore/constants.py
jaeger_client_contrib/thrift_gen/zipkincore/ttypes.py
jaeger_client_contrib/zipkin/__init__.py
jaeger_client_contrib/zipkin/codecs.py
jaeger_client_contrib/zipkin/reporter.py
tests/__init__.py
tests/conftest.py
tests/test_config.py
tests/test_sampler.py
tests/test_thrift.py
tests/test_tracer.py
tests/zipkin/__init__.py
tests/zipkin/test_codecs.py
tests/zipkin/test_reporter.py